llama/__ini__.py
llama/settings.py
llama/starter.py
llama_model-0.0.1.dist-info/METADATA
llama_model-0.0.1.dist-info/WHEEL
llama_model-0.0.1.dist-info/top_level.txt
llama_model-0.0.1.dist-info/RECORD
