Metadata-Version: 2.1
Name: llama_model
Version: 0.0.1
Summary: Get information from custom text
Home-page: 
Author: javad nematollahi
Author-email: javadnematollahi92@gmail.com
Classifier: Programming Language :: Python :: 3
Classifier: License :: OSI Approved :: MIT License
Classifier: Operating System :: OS Independent
